odoo10_addon_website_field_autocomplete-10.0.1.0.0-py2.7-nspkg.pth
odoo10_addon_website_field_autocomplete-10.0.1.0.0.dist-info/top_level.txt
odoo10_addon_website_field_autocomplete-10.0.1.0.0.dist-info/WHEEL
odoo10_addon_website_field_autocomplete-10.0.1.0.0.dist-info/RECORD
odoo10_addon_website_field_autocomplete-10.0.1.0.0.dist-info/metadata.json
odoo10_addon_website_field_autocomplete-10.0.1.0.0.dist-info/DESCRIPTION.rst
odoo10_addon_website_field_autocomplete-10.0.1.0.0.dist-info/METADATA
odoo10_addon_website_field_autocomplete-10.0.1.0.0.dist-info/namespace_packages.txt
odoo/addons/website_field_autocomplete/__manifest__.py
odoo/addons/website_field_autocomplete/__init__.py
odoo/addons/website_field_autocomplete/README.rst
odoo/addons/website_field_autocomplete/i18n/zh_CN.po
odoo/addons/website_field_autocomplete/i18n/nb_NO.po
odoo/addons/website_field_autocomplete/i18n/sl.po
odoo/addons/website_field_autocomplete/i18n/fr.po
odoo/addons/website_field_autocomplete/i18n/pt_BR.po
odoo/addons/website_field_autocomplete/views/assets.xml
odoo/addons/website_field_autocomplete/controllers/main.py
odoo/addons/website_field_autocomplete/controllers/__init__.py
odoo/addons/website_field_autocomplete/demo/field_autocomplete_demo.xml
odoo/addons/website_field_autocomplete/static/description/icon.png
odoo/addons/website_field_autocomplete/static/src/js/field_autocomplete.js
